{"timeGiven":120.0,"move":45,"score1":20000,"score2":50000,"score3":100000,"lstMissionFruitAmout":[{"name":"Qua_viet_quat","amount":60},{"name":"Qua_chanh","amount":60}],"targetTime":false,"targetMove":true,"taregtScore":true,"targetFruit":false,"targetBug":true,"targetBom":false,"loaiqua":["Qua_viet_quat","Qua_na","Qua_man","Qua_chanh"],"soluongSau":[10,10],"soluongBom":10,"num":[0,8,0,8,0,8,0,8,0,8,0,8,0,8,0,8,0,8,0,8,0,8,0,8,0,8,0,8,0,8,0,8,0,8,0,8,0,8,0,8,0,8,0,8,0,8,0,8,0,8,0,8,0,8,0,8,0,8,0,8,0,8,0,8,0,8,0,8,0,8,0,8,0,8,0,8,0,8,0,8,0]}